spi_master.v
module spi_master #(
    parameter DATA_WIDTH = 8
)(
    input  wire                    clk,
    input  wire                    rst_n,
    input  wire [7:0]              clk_div,
    input  wire                    cpol,
    input  wire                    cpha,
    input  wire [DATA_WIDTH-1:0]   tx_data,
    output reg  [DATA_WIDTH-1:0]   rx_data,
    input  wire                    tx_valid,
    output reg                     tx_ready,
    output reg                     spi_mosi,
    input  wire                    spi_miso,
    output reg                     spi_sclk,
    output reg                     spi_ss_n
);

    localparam IDLE  = 2'b00;
    localparam SETUP = 2'b01;
    localparam TRANSFER = 2'b10;
    localparam DONE  = 2'b11;
    
    reg [1:0] state, next_state;
    reg [7:0] clk_counter;
    reg [4:0] bit_counter;
    reg [DATA_WIDTH-1:0] tx_shift_reg;
    reg [DATA_WIDTH-1:0] rx_shift_reg;
    reg sclk_enable;
    
    always @(posedge clk or negedge rst_n) begin
        if (!rst_n) begin
            clk_counter <= 8'd0;
            spi_sclk <= cpol;
        end else begin
            if (sclk_enable) begin
                if (clk_counter >= clk_div) begin
                    clk_counter <= 8'd0;
                    spi_sclk <= ~spi_sclk;
                end else begin
                    clk_counter <= clk_counter + 1'b1;
                end
            end else begin
                clk_counter <= 8'd0;
                spi_sclk <= cpol;
            end
        end
    end
    
    always @(posedge clk or negedge rst_n) begin
        if (!rst_n)
            state <= IDLE;
        else
            state <= next_state;
    end
    
    always @(*) begin
        next_state = state;
        case (state)
            IDLE: begin
                if (tx_valid)
                    next_state = SETUP;
            end
            SETUP: begin
                next_state = TRANSFER;
            end
            TRANSFER: begin
                if (bit_counter >= DATA_WIDTH)
                    next_state = DONE;
            end
            DONE: begin
                next_state = IDLE;
            end
        endcase
    end
    
    always @(posedge clk or negedge rst_n) begin
        if (!rst_n) begin
            tx_ready <= 1'b1;
            spi_ss_n <= 1'b1;
            spi_mosi <= 1'b0;
            bit_counter <= 5'd0;
            tx_shift_reg <= {DATA_WIDTH{1'b0}};
            rx_shift_reg <= {DATA_WIDTH{1'b0}};
            rx_data <= {DATA_WIDTH{1'b0}};
            sclk_enable <= 1'b0;
        end else begin
            case (state)
                IDLE: begin
                    tx_ready <= 1'b1;
                    spi_ss_n <= 1'b1;
                    bit_counter <= 5'd0;
                    sclk_enable <= 1'b0;
                    if (tx_valid) begin
                        tx_shift_reg <= tx_data;
                        tx_ready <= 1'b0;
                    end
                end
                
                SETUP: begin
                    spi_ss_n <= 1'b0;
                    sclk_enable <= 1'b1;
                end
                
                TRANSFER: begin
                    if (clk_counter == 8'd0) begin
                        if (!cpha && !spi_sclk) begin
                            spi_mosi <= tx_shift_reg[DATA_WIDTH-1];
                            tx_shift_reg <= {tx_shift_reg[DATA_WIDTH-2:0], 1'b0};
                        end else if (!cpha && spi_sclk) begin
                            rx_shift_reg <= {rx_shift_reg[DATA_WIDTH-2:0], spi_miso};
                            bit_counter <= bit_counter + 1'b1;
                        end
                        
                        if (cpha && spi_sclk) begin
                            spi_mosi <= tx_shift_reg[DATA_WIDTH-1];
                            tx_shift_reg <= {tx_shift_reg[DATA_WIDTH-2:0], 1'b0};
                        end else if (cpha && !spi_sclk) begin
                            rx_shift_reg <= {rx_shift_reg[DATA_WIDTH-2:0], spi_miso};
                            bit_counter <= bit_counter + 1'b1;
                        end
                    end
                end
                
                DONE: begin
                    sclk_enable <= 1'b0;
                    spi_ss_n <= 1'b1;
                    rx_data <= rx_shift_reg;
                end
            endcase
        end
    end

endmodule

spi_master_tb.v
`timescale 1ns/1ps

module spi_master_tb;

    parameter CLK_PERIOD = 10;
    parameter DATA_WIDTH = 8;
    
    reg                    clk;
    reg                    rst_n;
    reg  [7:0]             clk_div;
    reg                    cpol;
    reg                    cpha;
    reg  [DATA_WIDTH-1:0]  tx_data;
    wire [DATA_WIDTH-1:0]  rx_data;
    reg                    tx_valid;
    wire                   tx_ready;
    wire                   spi_mosi;
    reg                    spi_miso;
    wire                   spi_sclk;
    wire                   spi_ss_n;
    
    spi_master #(
        .DATA_WIDTH(DATA_WIDTH)
    ) dut (
        .clk(clk),
        .rst_n(rst_n),
        .clk_div(clk_div),
        .cpol(cpol),
        .cpha(cpha),
        .tx_data(tx_data),
        .rx_data(rx_data),
        .tx_valid(tx_valid),
        .tx_ready(tx_ready),
        .spi_mosi(spi_mosi),
        .spi_miso(spi_miso),
        .spi_sclk(spi_sclk),
        .spi_ss_n(spi_ss_n)
    );
    
    initial begin
        clk = 0;
        forever #(CLK_PERIOD/2) clk = ~clk;
    end
    
    initial begin
        rst_n = 0;
        clk_div = 8'd4;
        cpol = 0;
        cpha = 0;
        tx_data = 8'd0;
        tx_valid = 0;
        spi_miso = 0;
        
        $dumpfile("spi_master_tb.vcd");
        $dumpvars(0, spi_master_tb);
        
        #100;
        rst_n = 1;
        #100;
        
        $display("========================================");
        $display("Test 1: Sending 0xA5");
        $display("========================================");
        @(posedge clk);
        tx_data = 8'hA5;
        tx_valid = 1;
        @(posedge clk);
        tx_valid = 0;
        
        wait(tx_ready == 1);
        #1000;
        
        $display("========================================");
        $display("Test 2: Sending 0x5A");
        $display("========================================");
        @(posedge clk);
        tx_data = 8'h5A;
        tx_valid = 1;
        @(posedge clk);
        tx_valid = 0;
        
        wait(tx_ready == 1);
        #1000;
        
        $display("========================================");
        $display("Simulation Complete!");
        $display("========================================");
        $finish;
    end
    
    integer bit_cnt = 0;
    reg [7:0] slave_rx_data;
    always @(posedge spi_sclk or posedge spi_ss_n) begin
        if (spi_ss_n) begin
            bit_cnt = 0;
            slave_rx_data = 8'd0;
        end else begin
            if (bit_cnt < 8) begin
                slave_rx_data = {slave_rx_data[6:0], spi_mosi};
                spi_miso = ~spi_mosi;
                bit_cnt = bit_cnt + 1;
            end
        end
    end

endmodule

spi_master_tb.vcd
$date
	Sat Dec 20 17:12:38 2025
$end
$version
	Icarus Verilog
$end
$timescale
	1ps
$end
$scope module spi_master_tb $end
$var wire 1 ! tx_ready $end
$var wire 1 " spi_ss_n $end
$var wire 1 # spi_sclk $end
$var wire 1 $ spi_mosi $end
$var wire 8 % rx_data [7:0] $end
$var reg 1 & clk $end
$var reg 8 ' clk_div [7:0] $end
$var reg 1 ( cpha $end
$var reg 1 ) cpol $end
$var reg 1 * rst_n $end
$var reg 8 + slave_rx_data [7:0] $end
$var reg 1 , spi_miso $end
$var reg 8 - tx_data [7:0] $end
$var reg 1 . tx_valid $end
$var integer 32 / bit_cnt [31:0] $end
$scope module dut $end
$var wire 1 & clk $end
$var wire 8 0 clk_div [7:0] $end
$var wire 1 ( cpha $end
$var wire 1 ) cpol $end
$var wire 1 * rst_n $end
$var wire 1 , spi_miso $end
$var wire 8 1 tx_data [7:0] $end
$var wire 1 . tx_valid $end
$var reg 5 2 bit_counter [4:0] $end
$var reg 8 3 clk_counter [7:0] $end
$var reg 2 4 next_state [1:0] $end
$var reg 8 5 rx_data [7:0] $end
$var reg 8 6 rx_shift_reg [7:0] $end
$var reg 1 7 sclk_enable $end
$var reg 1 $ spi_mosi $end
$var reg 1 # spi_sclk $end
$var reg 1 " spi_ss_n $end
$var reg 2 8 state [1:0] $end
$var reg 1 ! tx_ready $end
$var reg 8 9 tx_shift_reg [7:0] $end
$upscope $end
$upscope $end
$enddefinitions $end
#0
$dumpvars
b0 9
b0 8
07
b0 6
b0 5
b0 4
b0 3
b0 2
b0 1
b100 0
b0 /
0.
b0 -
0,
b0 +
0*
0)
0(
b100 '
0&
b0 %
0$
0#
1"
1!
$end
#5000
1&
#10000
0&
#15000
1&
#20000
0&
#25000
1&
#30000
0&
#35000
1&
#40000
0&
#45000
1&
#50000
0&
#55000
1&
#60000
0&
#65000
1&
#70000
0&
#75000
1&
#80000
0&
#85000
1&
#90000
0&
#95000
1&
#100000
0&
1*
#105000
1&
#110000
0&
#115000
1&
#120000
0&
#125000
1&
#130000
0&
#135000
1&
#140000
0&
#145000
1&
#150000
0&
#155000
1&
#160000
0&
#165000
1&
#170000
0&
#175000
1&
#180000
0&
#185000
1&
#190000
0&
#195000
1&
#200000
0&
#205000
0!
b10100101 9
b1 4
1.
b10100101 -
b10100101 1
1&
#210000
0&
#215000
b1 8
1!
b10 4
0.
1&
#220000
0&
#225000
17
0"
b10 8
1&
#230000
0&
#235000
b1 3
b1001010 9
1$
1&
#240000
0&
#245000
b10 3
1&
#250000
0&
#255000
b11 3
1&
#260000
0&
#265000
b100 3
1&
#270000
0&
#275000
b1 /
b1 +
1#
b0 3
1&
#280000
0&
#285000
b1 2
b1 3
1&
#290000
0&
#295000
b10 3
1&
#300000
0&
#305000
b11 3
1&
#310000
0&
#315000
b100 3
1&
#320000
0&
#325000
0#
b0 3
1&
#330000
0&
#335000
b1 3
b10010100 9
0$
1&
#340000
0&
#345000
b10 3
1&
#350000
0&
#355000
b11 3
1&
#360000
0&
#365000
b100 3
1&
#370000
0&
#375000
b10 /
1,
b10 +
1#
b0 3
1&
#380000
0&
#385000
b10 2
b1 6
b1 3
1&
#390000
0&
#395000
b10 3
1&
#400000
0&
#405000
b11 3
1&
#410000
0&
#415000
b100 3
1&
#420000
0&
#425000
0#
b0 3
1&
#430000
0&
#435000
b1 3
b101000 9
1$
1&
#440000
0&
#445000
b10 3
1&
#450000
0&
#455000
b11 3
1&
#460000
0&
#465000
b100 3
1&
#470000
0&
#475000
b11 /
0,
b101 +
1#
b0 3
1&
#480000
0&
#485000
b11 2
b10 6
b1 3
1&
#490000
0&
#495000
b10 3
1&
#500000
0&
#505000
b11 3
1&
#510000
0&
#515000
b100 3
1&
#520000
0&
#525000
0#
b0 3
1&
#530000
0&
#535000
b1 3
b1010000 9
0$
1&
#540000
0&
#545000
b10 3
1&
#550000
0&
#555000
b11 3
1&
#560000
0&
#565000
b100 3
1&
#570000
0&
#575000
b100 /
1,
b1010 +
1#
b0 3
1&
#580000
0&
#585000
b100 2
b101 6
b1 3
1&
#590000
0&
#595000
b10 3
1&
#600000
0&
#605000
b11 3
1&
#610000
0&
#615000
b100 3
1&
#620000
0&
#625000
0#
b0 3
1&
#630000
0&
#635000
b1 3
b10100000 9
1&
#640000
0&
#645000
b10 3
1&
#650000
0&
#655000
b11 3
1&
#660000
0&
#665000
b100 3
1&
#670000
0&
#675000
b101 /
b10100 +
1#
b0 3
1&
#680000
0&
#685000
b101 2
b1011 6
b1 3
1&
#690000
0&
#695000
b10 3
1&
#700000
0&
#705000
b11 3
1&
#710000
0&
#715000
b100 3
1&
#720000
0&
#725000
0#
b0 3
1&
#730000
0&
#735000
b1 3
b1000000 9
1$
1&
#740000
0&
#745000
b10 3
1&
#750000
0&
#755000
b11 3
1&
#760000
0&
#765000
b100 3
1&
#770000
0&
#775000
b110 /
0,
b101001 +
1#
b0 3
1&
#780000
0&
#785000
b110 2
b10110 6
b1 3
1&
#790000
0&
#795000
b10 3
1&
#800000
0&
#805000
b11 3
1&
#810000
0&
#815000
b100 3
1&
#820000
0&
#825000
0#
b0 3
1&
#830000
0&
#835000
b1 3
b10000000 9
0$
1&
#840000
0&
#845000
b10 3
1&
#850000
0&
#855000
b11 3
1&
#860000
0&
#865000
b100 3
1&
#870000
0&
#875000
b111 /
1,
b1010010 +
1#
b0 3
1&
#880000
0&
#885000
b111 2
b101101 6
b1 3
1&
#890000
0&
#895000
b10 3
1&
#900000
0&
#905000
b11 3
1&
#910000
0&
#915000
b100 3
1&
#920000
0&
#925000
0#
b0 3
1&
#930000
0&
#935000
b1 3
b0 9
1$
1&
#940000
0&
#945000
b10 3
1&
#950000
0&
#955000
b11 3
1&
#960000
0&
#965000
b100 3
1&
#970000
0&
#975000
b1000 /
0,
b10100101 +
1#
b0 3
1&
#980000
0&
#985000
b11 4
b1000 2
b1011010 6
b1 3
1&
#990000
0&
#995000
b0 4
b10 3
b11 8
1&
#1000000
0&
#1005000
b0 +
b0 /
b1011010 %
b1011010 5
1"
07
b0 8
b11 3
1&
#1010000
0&
#1015000
0#
b0 3
b0 2
1&
#1020000
0&
#1025000
1&
#1030000
0&
#1035000
1&
#1040000
0&
#1045000
1&
#1050000
0&
#1055000
1&
#1060000
0&
#1065000
1&
#1070000
0&
#1075000
1&
#1080000
0&
#1085000
1&
#1090000
0&
#1095000
1&
#1100000
0&
#1105000
1&
#1110000
0&
#1115000
1&
#1120000
0&
#1125000
1&
#1130000
0&
#1135000
1&
#1140000
0&
#1145000
1&
#1150000
0&
#1155000
1&
#1160000
0&
#1165000
1&
#1170000
0&
#1175000
1&
#1180000
0&
#1185000
1&
#1190000
0&
#1195000
1&
#1200000
0&
#1205000
1&
#1210000
0&
#1215000
0!
b1011010 9
b1 4
1.
b1011010 -
b1011010 1
1&
#1220000
0&
#1225000
1!
b1 8
b10 4
0.
1&
#1230000
0&
#1235000
b10 8
17
0"
1&
#1240000
0&
#1245000
b10110100 9
0$
b1 3
1&
#1250000
0&
#1255000
b10 3
1&
#1260000
0&
#1265000
b11 3
1&
#1270000
0&
#1275000
b100 3
1&
#1280000
0&
#1285000
b1 /
1,
1#
b0 3
1&
#1290000
0&
#1295000
b1 3
b1 2
b10110101 6
1&
#1300000
0&
#1305000
b10 3
1&
#1310000
0&
#1315000
b11 3
1&
#1320000
0&
#1325000
b100 3
1&
#1330000
0&
#1335000
0#
b0 3
1&
#1340000
0&
#1345000
b1101000 9
1$
b1 3
1&
#1350000
0&
#1355000
b10 3
1&
#1360000
0&
#1365000
b11 3
1&
#1370000
0&
#1375000
b100 3
1&
#1380000
0&
#1385000
b10 /
0,
b1 +
1#
b0 3
1&
#1390000
0&
#1395000
b1 3
b10 2
b1101010 6
1&
#1400000
0&
#1405000
b10 3
1&
#1410000
0&
#1415000
b11 3
1&
#1420000
0&
#1425000
b100 3
1&
#1430000
0&
#1435000
0#
b0 3
1&
#1440000
0&
#1445000
b11010000 9
0$
b1 3
1&
#1450000
0&
#1455000
b10 3
1&
#1460000
0&
#1465000
b11 3
1&
#1470000
0&
#1475000
b100 3
1&
#1480000
0&
#1485000
b11 /
1,
b10 +
1#
b0 3
1&
#1490000
0&
#1495000
b1 3
b11 2
b11010101 6
1&
#1500000
0&
#1505000
b10 3
1&
#1510000
0&
#1515000
b11 3
1&
#1520000
0&
#1525000
b100 3
1&
#1530000
0&
#1535000
0#
b0 3
1&
#1540000
0&
#1545000
b10100000 9
1$
b1 3
1&
#1550000
0&
#1555000
b10 3
1&
#1560000
0&
#1565000
b11 3
1&
#1570000
0&
#1575000
b100 3
1&
#1580000
0&
#1585000
b100 /
0,
b101 +
1#
b0 3
1&
#1590000
0&
#1595000
b1 3
b100 2
b10101010 6
1&
#1600000
0&
#1605000
b10 3
1&
#1610000
0&
#1615000
b11 3
1&
#1620000
0&
#1625000
b100 3
1&
#1630000
0&
#1635000
0#
b0 3
1&
#1640000
0&
#1645000
b1000000 9
b1 3
1&
#1650000
0&
#1655000
b10 3
1&
#1660000
0&
#1665000
b11 3
1&
#1670000
0&
#1675000
b100 3
1&
#1680000
0&
#1685000
b101 /
b1011 +
1#
b0 3
1&
#1690000
0&
#1695000
b1 3
b101 2
b1010100 6
1&
#1700000
0&
#1705000
b10 3
1&
#1710000
0&
#1715000
b11 3
1&
#1720000
0&
#1725000
b100 3
1&
#1730000
0&
#1735000
0#
b0 3
1&
#1740000
0&
#1745000
b10000000 9
0$
b1 3
1&
#1750000
0&
#1755000
b10 3
1&
#1760000
0&
#1765000
b11 3
1&
#1770000
0&
#1775000
b100 3
1&
#1780000
0&
#1785000
b110 /
1,
b10110 +
1#
b0 3
1&
#1790000
0&
#1795000
b1 3
b110 2
b10101001 6
1&
#1800000
0&
#1805000
b10 3
1&
#1810000
0&
#1815000
b11 3
1&
#1820000
0&
#1825000
b100 3
1&
#1830000
0&
#1835000
0#
b0 3
1&
#1840000
0&
#1845000
b0 9
1$
b1 3
1&
#1850000
0&
#1855000
b10 3
1&
#1860000
0&
#1865000
b11 3
1&
#1870000
0&
#1875000
b100 3
1&
#1880000
0&
#1885000
b111 /
0,
b101101 +
1#
b0 3
1&
#1890000
0&
#1895000
b1 3
b111 2
b1010010 6
1&
#1900000
0&
#1905000
b10 3
1&
#1910000
0&
#1915000
b11 3
1&
#1920000
0&
#1925000
b100 3
1&
#1930000
0&
#1935000
0#
b0 3
1&
#1940000
0&
#1945000
0$
b1 3
1&
#1950000
0&
#1955000
b10 3
1&
#1960000
0&
#1965000
b11 3
1&
#1970000
0&
#1975000
b100 3
1&
#1980000
0&
#1985000
b1000 /
1,
b1011010 +
1#
b0 3
1&
#1990000
0&
#1995000
b11 4
b1 3
b1000 2
b10100101 6
1&
#2000000
0&
#2005000
b0 4
b11 8
b10 3
1&
#2010000
0&
#2015000
b0 +
b0 /
b11 3
b0 8
b10100101 %
b10100101 5
1"
07
1&
#2020000
0&
#2025000
b0 2
0#
b0 3
1&
